hanifx/__init__.py
hanifx/detector.py
hanifx/enc/__init__.py
hanifx/enc/base_layer.py
hanifx/enc/chain_layer.py
hanifx/enc/cli_enc.py
hanifx/enc/filewriter.py
hanifx/enc/id_layer.py
hanifx/enc/integrity.py
hanifx/enc/keygen.py
hanifx/enc/locked.py
hanifx/enc/logic_layer.py
hanifx/enc/padder.py
hanifx/enc/smart.py
hanifx/enc/time_layer.py
hanifx_anti/__init__.py
hanifx_anti-10.0.1.dist-info/licenses/LICENSE
hanifx_anti-10.0.1.dist-info/METADATA
hanifx_anti-10.0.1.dist-info/WHEEL
hanifx_anti-10.0.1.dist-info/entry_points.txt
hanifx_anti-10.0.1.dist-info/top_level.txt
hanifx_anti-10.0.1.dist-info/RECORD
