Metadata-Version: 2.4
Name: hanifx_anti
Version: 10.0.1
Summary: Ultimate Phone Security & Anti-Malware System
Author: Hanif
Author-email: sajim4653@gmail.com
License-File: LICENSE
Requires-Dist: cryptography
Requires-Dist: scapy
Requires-Dist: psutil
Requires-Dist: requests
Dynamic: author
Dynamic: author-email
Dynamic: license-file
Dynamic: requires-dist
Dynamic: summary
